growtopia/__init__.py
growtopia/_version.py
growtopia/dataminer/__init__.py
growtopia/dataminer/bin/7z.dll
growtopia/dataminer/bin/7z.exe
growtopia/dataminer/bin/License.txt
growtopia/growtopia_info/__init__.py
growtopia/growtopia_info/render_world.py
growtopia/growtopia_info/status.py
growtopia/itemsdat_parser/__init__.py
growtopia/itemsdat_parser/template.py
growtopia/rttex_converter/__init__.py
growtopia/wiki/__init__.py
growtopia_api-0.2.3.dist-info/licenses/LICENSE
growtopia_api-0.2.3.dist-info/METADATA
growtopia_api-0.2.3.dist-info/WHEEL
growtopia_api-0.2.3.dist-info/top_level.txt
growtopia_api-0.2.3.dist-info/RECORD
