Metadata-Version: 2.4
Name: growtopia-api
Version: 0.2.3
Summary: Unofficial 🌲 Growtopia API providing powerful tools to access item data, sprites, and other resources.
Author-email: Harvan Nurluthfi <harvan.nurluthfi@gmail.com>
License: MIT License
Project-URL: Repository, https://github.com/H-pun/growtopia-api
Keywords: Growtopia
Classifier: Development Status :: 4 - Beta
Classifier: Programming Language :: Python
Classifier: Programming Language :: Python :: 3.10
Classifier: Programming Language :: Python :: 3.11
Classifier: Programming Language :: Python :: 3.12
Classifier: Intended Audience :: Developers
Classifier: License :: OSI Approved :: MIT License
Requires-Python: >=3.10
License-File: LICENSE
Requires-Dist: requests
Requires-Dist: beautifulsoup4
Requires-Dist: pytz
Requires-Dist: tqdm
Requires-Dist: pillow
Dynamic: license-file
